CloudConfig/__init__.py
VerdisCloudConfig-0.0.3.dist-info/LICENSE.txt
VerdisCloudConfig-0.0.3.dist-info/METADATA
VerdisCloudConfig-0.0.3.dist-info/WHEEL
VerdisCloudConfig-0.0.3.dist-info/top_level.txt
VerdisCloudConfig-0.0.3.dist-info/RECORD
