Metadata-Version: 2.1
Name: VerdisCloudConfig
Version: 0.0.3
Summary: Fetching the configurations
Author: SHIVAM PAHWA
Author-email: shivam@verdis.ai
Classifier: Programming Language :: Python :: 3
Classifier: License :: OSI Approved :: MIT License
Classifier: Operating System :: OS Independent
License-File: LICENSE.txt
